MANIFEST.in
README.md
setup.py
togeojsontiles/__init__.py
togeojsontiles/tiles.py
togeojsontiles.egg-info/PKG-INFO
togeojsontiles.egg-info/SOURCES.txt
togeojsontiles.egg-info/dependency_links.txt
togeojsontiles.egg-info/not-zip-safe
togeojsontiles.egg-info/top_level.txt