Metadata-Version: 1.1
Name: togeojsontiles
Version: 0.1.2
Summary: Create geojson-tiles from gpx or geojson using tippecanoe (C++) and togeojson (javascript)
Home-page: http://github.com/bartromgens/togeojsontiles
Author: Bart Römgens
Author-email: bart.romgens@gmail.com
License: MIT
Keywords: gis geojson tippecanoe tiles map-tiles mbtiles gpx
Platform: UNKNOWN
Classifier: Development Status :: 4 - Beta
Classifier: Intended Audience :: Developers
Classifier: License :: OSI Approved :: MIT License
Classifier: Programming Language :: Python :: 3
Classifier: Programming Language :: Python :: 3.3
Classifier: Programming Language :: Python :: 3.4
Classifier: Programming Language :: Python :: 3.5
